{"dependencies":[{"name":"D:\\Projects\\PlantIn - test\\package.json","includedInParent":true,"mtime":1639314539830}],"generated":{"js":"var fetchWeather = function () {\n\tvar _ref = _asyncToGenerator( /*#__PURE__*/regeneratorRuntime.mark(function _callee() {\n\t\tvar key, city, url;\n\t\treturn regeneratorRuntime.wrap(function _callee$(_context) {\n\t\t\twhile (1) {\n\t\t\t\tswitch (_context.prev = _context.next) {\n\t\t\t\t\tcase 0:\n\t\t\t\t\t\tkey = 'dd47af45cbc9862e2129c021a8f27e21';\n\t\t\t\t\t\tcity = 'Kyiv';\n\t\t\t\t\t\turl = 'api.openweathermap.org/data/2.5/weather?q=' + city + '&appid=' + key;\n\t\t\t\t\t\t//fetch the weather\n\n\t\t\t\t\t\tfetch(url).then(function (response) {\n\t\t\t\t\t\t\treturn response.json();\n\t\t\t\t\t\t}).then(function (data) {\n\t\t\t\t\t\t\tJSON.parse(data);\n\t\t\t\t\t\t\tconsole.log(data);\n\t\t\t\t\t\t});\n\n\t\t\t\t\tcase 4:\n\t\t\t\t\tcase 'end':\n\t\t\t\t\t\treturn _context.stop();\n\t\t\t\t}\n\t\t\t}\n\t\t}, _callee, this);\n\t}));\n\n\treturn function fetchWeather() {\n\t\treturn _ref.apply(this, arguments);\n\t};\n}();\n\nfunction _asyncToGenerator(fn) { return function () { var gen = fn.apply(this, arguments); return new Promise(function (resolve, reject) { function step(key, arg) { try { var info = gen[key](arg); var value = info.value; } catch (error) { reject(error); return; } if (info.done) { resolve(value); } else { return Promise.resolve(value).then(function (value) { step(\"next\", value); }, function (err) { step(\"throw\", err); }); } } return step(\"next\"); }); }; }\n\nvar text = document.querySelector('.temperature');\n\nconsole.log(text);\n\nfetchWeather();","map":{"mappings":[{"generated":{"line":2,"column":68},"source":"javascript\\weatherAPI.js","original":{"line":5,"column":0}},{"generated":{"line":3,"column":0},"source":"javascript\\weatherAPI.js","original":{"line":5,"column":0}},{"generated":{"line":4,"column":0},"source":"javascript\\weatherAPI.js","original":{"line":5,"column":0}},{"generated":{"line":5,"column":0},"source":"javascript\\weatherAPI.js","original":{"line":5,"column":0}},{"generated":{"line":6,"column":0},"source":"javascript\\weatherAPI.js","original":{"line":5,"column":0}},{"generated":{"line":7,"column":0},"source":"javascript\\weatherAPI.js","original":{"line":5,"column":0}},{"name":"key","generated":{"line":8,"column":0},"source":"javascript\\weatherAPI.js","original":{"line":6,"column":5}},{"generated":{"line":8,"column":9},"source":"javascript\\weatherAPI.js","original":{"line":5,"column":0}},{"generated":{"line":8,"column":12},"source":"javascript\\weatherAPI.js","original":{"line":6,"column":11}},{"generated":{"line":8,"column":46},"source":"javascript\\weatherAPI.js","original":{"line":5,"column":0}},{"name":"city","generated":{"line":9,"column":0},"source":"javascript\\weatherAPI.js","original":{"line":7,"column":5}},{"generated":{"line":9,"column":10},"source":"javascript\\weatherAPI.js","original":{"line":5,"column":0}},{"generated":{"line":9,"column":13},"source":"javascript\\weatherAPI.js","original":{"line":7,"column":12}},{"generated":{"line":9,"column":19},"source":"javascript\\weatherAPI.js","original":{"line":5,"column":0}},{"name":"url","generated":{"line":10,"column":0},"source":"javascript\\weatherAPI.js","original":{"line":8,"column":5}},{"generated":{"line":10,"column":9},"source":"javascript\\weatherAPI.js","original":{"line":5,"column":0}},{"name":"city","generated":{"line":10,"column":59},"source":"javascript\\weatherAPI.js","original":{"line":8,"column":56}},{"generated":{"line":10,"column":63},"source":"javascript\\weatherAPI.js","original":{"line":5,"column":0}},{"name":"key","generated":{"line":10,"column":78},"source":"javascript\\weatherAPI.js","original":{"line":8,"column":70}},{"generated":{"line":10,"column":81},"source":"javascript\\weatherAPI.js","original":{"line":5,"column":0}},{"generated":{"line":11,"column":0},"source":"javascript\\weatherAPI.js","original":{"line":9,"column":1}},{"name":"fetch","generated":{"line":13,"column":0},"source":"javascript\\weatherAPI.js","original":{"line":10,"column":1}},{"name":"url","generated":{"line":13,"column":12},"source":"javascript\\weatherAPI.js","original":{"line":10,"column":7}},{"generated":{"line":13,"column":15},"source":"javascript\\weatherAPI.js","original":{"line":10,"column":1}},{"name":"then","generated":{"line":13,"column":17},"source":"javascript\\weatherAPI.js","original":{"line":11,"column":3}},{"generated":{"line":13,"column":21},"source":"javascript\\weatherAPI.js","original":{"line":10,"column":1}},{"generated":{"line":13,"column":22},"source":"javascript\\weatherAPI.js","original":{"line":11,"column":8}},{"generated":{"line":13,"column":42},"source":"javascript\\weatherAPI.js","original":{"line":11,"column":20}},{"generated":{"line":14,"column":0},"source":"javascript\\weatherAPI.js","original":{"line":12,"column":3}},{"name":"response","generated":{"line":14,"column":14},"source":"javascript\\weatherAPI.js","original":{"line":12,"column":10}},{"name":"json","generated":{"line":14,"column":23},"source":"javascript\\weatherAPI.js","original":{"line":12,"column":19}},{"generated":{"line":14,"column":27},"source":"javascript\\weatherAPI.js","original":{"line":12,"column":10}},{"generated":{"line":14,"column":29},"source":"javascript\\weatherAPI.js","original":{"line":12,"column":3}},{"generated":{"line":15,"column":0},"source":"javascript\\weatherAPI.js","original":{"line":13,"column":3}},{"generated":{"line":15,"column":7},"source":"javascript\\weatherAPI.js","original":{"line":10,"column":1}},{"name":"then","generated":{"line":15,"column":9},"source":"javascript\\weatherAPI.js","original":{"line":14,"column":3}},{"generated":{"line":15,"column":13},"source":"javascript\\weatherAPI.js","original":{"line":10,"column":1}},{"generated":{"line":15,"column":14},"source":"javascript\\weatherAPI.js","original":{"line":14,"column":8}},{"generated":{"line":15,"column":30},"source":"javascript\\weatherAPI.js","original":{"line":14,"column":16}},{"name":"JSON","generated":{"line":16,"column":0},"source":"javascript\\weatherAPI.js","original":{"line":15,"column":3}},{"name":"parse","generated":{"line":16,"column":12},"source":"javascript\\weatherAPI.js","original":{"line":15,"column":8}},{"generated":{"line":16,"column":17},"source":"javascript\\weatherAPI.js","original":{"line":15,"column":3}},{"name":"data","generated":{"line":16,"column":18},"source":"javascript\\weatherAPI.js","original":{"line":15,"column":14}},{"generated":{"line":16,"column":22},"source":"javascript\\weatherAPI.js","original":{"line":15,"column":3}},{"name":"console","generated":{"line":17,"column":0},"source":"javascript\\weatherAPI.js","original":{"line":16,"column":3}},{"name":"log","generated":{"line":17,"column":15},"source":"javascript\\weatherAPI.js","original":{"line":16,"column":11}},{"generated":{"line":17,"column":18},"source":"javascript\\weatherAPI.js","original":{"line":16,"column":3}},{"name":"data","generated":{"line":17,"column":19},"source":"javascript\\weatherAPI.js","original":{"line":16,"column":15}},{"generated":{"line":17,"column":23},"source":"javascript\\weatherAPI.js","original":{"line":16,"column":3}},{"generated":{"line":18,"column":0},"source":"javascript\\weatherAPI.js","original":{"line":17,"column":3}},{"generated":{"line":18,"column":7},"source":"javascript\\weatherAPI.js","original":{"line":10,"column":1}},{"generated":{"line":20,"column":0},"source":"javascript\\weatherAPI.js","original":{"line":5,"column":0}},{"generated":{"line":21,"column":0},"source":"javascript\\weatherAPI.js","original":{"line":5,"column":0}},{"generated":{"line":22,"column":0},"source":"javascript\\weatherAPI.js","original":{"line":5,"column":0}},{"generated":{"line":23,"column":0},"source":"javascript\\weatherAPI.js","original":{"line":5,"column":0}},{"generated":{"line":24,"column":0},"source":"javascript\\weatherAPI.js","original":{"line":5,"column":0}},{"generated":{"line":25,"column":0},"source":"javascript\\weatherAPI.js","original":{"line":5,"column":0}},{"generated":{"line":26,"column":0},"source":"javascript\\weatherAPI.js","original":{"line":5,"column":0}},{"name":"fetchWeather","generated":{"line":28,"column":17},"source":"javascript\\weatherAPI.js","original":{"line":5,"column":15}},{"generated":{"line":35,"column":0},"source":"javascript\\weatherAPI.js","original":{"line":1,"column":0}},{"name":"text","generated":{"line":35,"column":4},"source":"javascript\\weatherAPI.js","original":{"line":1,"column":4}},{"name":"document","generated":{"line":35,"column":11},"source":"javascript\\weatherAPI.js","original":{"line":1,"column":11}},{"name":"querySelector","generated":{"line":35,"column":20},"source":"javascript\\weatherAPI.js","original":{"line":1,"column":20}},{"generated":{"line":35,"column":33},"source":"javascript\\weatherAPI.js","original":{"line":1,"column":11}},{"generated":{"line":35,"column":34},"source":"javascript\\weatherAPI.js","original":{"line":1,"column":34}},{"generated":{"line":35,"column":48},"source":"javascript\\weatherAPI.js","original":{"line":1,"column":11}},{"generated":{"line":35,"column":49},"source":"javascript\\weatherAPI.js","original":{"line":1,"column":0}},{"name":"console","generated":{"line":37,"column":0},"source":"javascript\\weatherAPI.js","original":{"line":3,"column":0}},{"name":"log","generated":{"line":37,"column":8},"source":"javascript\\weatherAPI.js","original":{"line":3,"column":8}},{"generated":{"line":37,"column":11},"source":"javascript\\weatherAPI.js","original":{"line":3,"column":0}},{"name":"text","generated":{"line":37,"column":12},"source":"javascript\\weatherAPI.js","original":{"line":3,"column":12}},{"generated":{"line":37,"column":16},"source":"javascript\\weatherAPI.js","original":{"line":3,"column":0}},{"name":"fetchWeather","generated":{"line":39,"column":0},"source":"javascript\\weatherAPI.js","original":{"line":20,"column":0}}],"sources":{"javascript\\weatherAPI.js":"let text = document.querySelector('.temperature');\r\n\r\nconsole.log(text);\r\n\r\nasync function fetchWeather() {\r\n\tlet key = 'dd47af45cbc9862e2129c021a8f27e21';\r\n\tlet city = 'Kyiv';\r\n\tlet url = `api.openweathermap.org/data/2.5/weather?q=${city}&appid=${key}`;\r\n\t//fetch the weather\r\n\tfetch(url)\r\n\t\t.then(response => {\r\n\t\t\treturn response.json();\r\n\t\t})\r\n\t\t.then(data => {\r\n\t\t\tJSON.parse(data);\r\n\t\t\tconsole.log(data);\r\n\t\t});\r\n}\r\n\r\nfetchWeather();\r\n"},"lineCount":null}},"hash":"231c26e150a0a8d02cdaa0c798334b63","cacheData":{"env":{}},"id":100}